foliant/cli/src.py
foliant/config/from.py
foliant/preprocessors/includesmap.py
foliant/preprocessors/repolink.py
foliantcontrib_multiproject-1.0.16.dist-info/licenses/LICENSE
foliantcontrib_multiproject-1.0.16.dist-info/METADATA
foliantcontrib_multiproject-1.0.16.dist-info/WHEEL
foliantcontrib_multiproject-1.0.16.dist-info/top_level.txt
foliantcontrib_multiproject-1.0.16.dist-info/RECORD
